{
  "id": "ed6941e1-4883-4bd4-b275-2cbcb2cf5e6a",
  "url": "/r4/ValueSet/$validate-code?",
  "method": "POST",
  "prod": {
    "status": 200,
    "contentType": "application/fhir+json",
    "size": 8605,
    "hash": "26fe831aa9a962548474e948fa796315"
  },
  "dev": {
    "status": 200,
    "contentType": "application/fhir+json; charset=utf-8",
    "size": 7081,
    "hash": "a87b0be2e688e1c3708c8859e30604a2"
  },
  "comparison": {
    "category": "content-differs",
    "op": "validate-code",
    "diffs": [
      {
        "type": "value-differs",
        "param": "issues"
      }
    ]
  },
  "prodBody": "{\"resourceType\" : \"Parameters\",\"parameter\" : [{\"name\" : \"version\",\"valueString\" : \"http://snomed.info/sct/900000000000207008/version/20250201\"},{\"name\" : \"version\",\"valueString\" : \"2024-12-05\"},{\"name\" : \"version\",\"valueString\" : \"2.81\"},{\"name\" : \"result\",\"valueBoolean\" : true},{\"name\" : \"system\",\"valueUri\" : \"http://loinc.org\"},{\"name\" : \"code\",\"valueCode\" : \"8310-5\"},{\"name\" : \"display\",\"valueString\" : \"Körpertemperatur\"},{\"name\" : \"message\",\"valueString\" : \"Wrong Display Name 'Body temperature - Core' for http://loinc.org#8329-5. Valid display is one of  choices: 'Body temperature - Core' (en-US), 'Body temperature - Core' (en-US), 'Bdy temp Core' (en-US), 'Core temperature' (en-US), 'temperatura corporal:temperatura:punto en el tiempo:centro:cuantitativo:' (es-AR), 'Temperatura corporal:Centro :Punto temporal:Temperatura:Cuantitativo:' (es-MX) or 'Bdy temp Core' (pt-BR) (for the language(s) 'de'); Wrong Display Name 'Body temperature - Core' for urn:iso:std:iso:11073:10101#150368. Valid display is 'MDC_TEMP_CORE' (for the language(s) 'de'); Wrong Display Name 'Body temperature' for http://loinc.org#8310-5. Valid display is one of 2 choices: 'Körpertemperatur' (de-AT) or 'Körpertemperatur' (de-DE) (for the language(s) 'de')\"},{\"name\" : \"codeableConcept\",\"valueCodeableConcept\" : {\"coding\" : [{\"system\" : \"http://loinc.org\",\"code\" : \"8310-5\",\"display\" : \"Body temperature\"},{\"system\" : \"http://snomed.info/sct\",\"code\" : \"276885007\",\"display\" : \"Core body temperature\"},{\"system\" : \"urn:iso:std:iso:11073:10101\",\"code\" : \"150364\"},{\"system\" : \"urn:iso:std:iso:11073:10101\",\"code\" : \"150368\",\"display\" : \"Body temperature - Core\"},{\"system\" : \"http://loinc.org\",\"code\" : \"8329-5\",\"display\" : \"Body temperature - Core\"}]}},{\"name\" : \"issues\",\"resource\" : {\"resourceType\" : \"OperationOutcome\",\"issue\" : [{\"extension\" : [{\"url\" : \"http://hl7.org/fhir/StructureDefinition/operationoutcome-message-id\",\"valueString\" : \"Display_Name_for__should_be_one_of__instead_of\"}],\"severity\" : \"warning\",\"code\" : \"invalid\",\"details\" : {\"coding\" : [{\"system\" : \"http://hl7.org/fhir/tools/CodeSystem/tx-issue-type\",\"code\" : \"invalid-display\"}],\"text\" : \"Wrong Display Name 'Body temperature' for http://loinc.org#8310-5. Valid display is one of 2 choices: 'Körpertemperatur' (de-AT) or 'Körpertemperatur' (de-DE) (for the language(s) 'de')\"},\"location\" : [\"CodeableConcept.coding[0].display\"],\"expression\" : [\"CodeableConcept.coding[0].display\"]},{\"extension\" : [{\"url\" : \"http://hl7.org/fhir/StructureDefinition/operationoutcome-message-id\",\"valueString\" : \"None_of_the_provided_codes_are_in_the_value_set_one\"}],\"severity\" : \"information\",\"code\" : \"code-invalid\",\"details\" : {\"coding\" : [{\"system\" : \"http://hl7.org/fhir/tools/CodeSystem/tx-issue-type\",\"code\" : \"this-code-not-in-vs\"}],\"text\" : \"The provided code 'http://snomed.info/sct#276885007 ('Core body temperature')' was not found in the value set 'http://hl7.org/fhir/ValueSet/observation-vitalsignresult|4.0.1'\"},\"location\" : [\"CodeableConcept.coding[1].code\"],\"expression\" : [\"CodeableConcept.coding[1].code\"]},{\"extension\" : [{\"url\" : \"http://hl7.org/fhir/StructureDefinition/operationoutcome-message-id\",\"valueString\" : \"None_of_the_provided_codes_are_in_the_value_set_one\"}],\"severity\" : \"information\",\"code\" : \"code-invalid\",\"details\" : {\"coding\" : [{\"system\" : \"http://hl7.org/fhir/tools/CodeSystem/tx-issue-type\",\"code\" : \"this-code-not-in-vs\"}],\"text\" : \"The provided code 'urn:iso:std:iso:11073:10101#150364' was not found in the value set 'http://hl7.org/fhir/ValueSet/observation-vitalsignresult|4.0.1'\"},\"location\" : [\"CodeableConcept.coding[2].code\"],\"expression\" : [\"CodeableConcept.coding[2].code\"]},{\"extension\" : [{\"url\" : \"http://hl7.org/fhir/StructureDefinition/operationoutcome-message-id\",\"valueString\" : \"MSG_DRAFT\"}],\"severity\" : \"information\",\"code\" : \"business-rule\",\"details\" : {\"coding\" : [{\"system\" : \"http://hl7.org/fhir/tools/CodeSystem/tx-issue-type\",\"code\" : \"status-check\"}],\"text\" : \"Reference to draft CodeSystem urn:iso:std:iso:11073:10101|2024-12-05 from fhir.tx.support.r4#0.32.0\"}},{\"extension\" : [{\"url\" : \"http://hl7.org/fhir/StructureDefinition/operationoutcome-message-id\",\"valueString\" : \"None_of_the_provided_codes_are_in_the_value_set_one\"}],\"severity\" : \"information\",\"code\" : \"code-invalid\",\"details\" : {\"coding\" : [{\"system\" : \"http://hl7.org/fhir/tools/CodeSystem/tx-issue-type\",\"code\" : \"this-code-not-in-vs\"}],\"text\" : \"The provided code 'urn:iso:std:iso:11073:10101#150368 ('Body temperature - Core')' was not found in the value set 'http://hl7.org/fhir/ValueSet/observation-vitalsignresult|4.0.1'\"},\"location\" : [\"CodeableConcept.coding[3].code\"],\"expression\" : [\"CodeableConcept.coding[3].code\"]},{\"extension\" : [{\"url\" : \"http://hl7.org/fhir/StructureDefinition/operationoutcome-message-id\",\"valueString\" : \"Display_Name_for__should_be_one_of__instead_of\"}],\"severity\" : \"warning\",\"code\" : \"invalid\",\"details\" : {\"coding\" : [{\"system\" : \"http://hl7.org/fhir/tools/CodeSystem/tx-issue-type\",\"code\" : \"invalid-display\"}],\"text\" : \"Wrong Display Name 'Body temperature - Core' for urn:iso:std:iso:11073:10101#150368. Valid display is 'MDC_TEMP_CORE' (for the language(s) 'de')\"},\"location\" : [\"CodeableConcept.coding[3].display\"],\"expression\" : [\"CodeableConcept.coding[3].display\"]},{\"extension\" : [{\"url\" : \"http://hl7.org/fhir/StructureDefinition/operationoutcome-message-id\",\"valueString\" : \"None_of_the_provided_codes_are_in_the_value_set_one\"}],\"severity\" : \"information\",\"code\" : \"code-invalid\",\"details\" : {\"coding\" : [{\"system\" : \"http://hl7.org/fhir/tools/CodeSystem/tx-issue-type\",\"code\" : \"this-code-not-in-vs\"}],\"text\" : \"The provided code 'http://loinc.org#8329-5 ('Body temperature - Core')' was not found in the value set 'http://hl7.org/fhir/ValueSet/observation-vitalsignresult|4.0.1'\"},\"location\" : [\"CodeableConcept.coding[4].code\"],\"expression\" : [\"CodeableConcept.coding[4].code\"]},{\"extension\" : [{\"url\" : \"http://hl7.org/fhir/StructureDefinition/operationoutcome-message-id\",\"valueString\" : \"Display_Name_for__should_be_one_of__instead_of\"}],\"severity\" : \"warning\",\"code\" : \"invalid\",\"details\" : {\"coding\" : [{\"system\" : \"http://hl7.org/fhir/tools/CodeSystem/tx-issue-type\",\"code\" : \"invalid-display\"}],\"text\" : \"Wrong Display Name 'Body temperature - Core' for http://loinc.org#8329-5. Valid display is one of  choices: 'Body temperature - Core' (en-US), 'Body temperature - Core' (en-US), 'Bdy temp Core' (en-US), 'Core temperature' (en-US), 'temperatura corporal:temperatura:punto en el tiempo:centro:cuantitativo:' (es-AR), 'Temperatura corporal:Centro :Punto temporal:Temperatura:Cuantitativo:' (es-MX) or 'Bdy temp Core' (pt-BR) (for the language(s) 'de')\"},\"location\" : [\"CodeableConcept.coding[4].display\"],\"expression\" : [\"CodeableConcept.coding[4].display\"]}]}},{\"name\" : \"diagnostics\",\"valueString\" : \"0 0 : start\\r\\n16 16   : 0ms  : Analysing http://hl7.org/fhir/ValueSet/observation-vitalsignresult|4.0.1 for validation purposes\\r\\n16 0    : 0ms  : Parameters: disp-lang=de, default-to-latest, display-warning\\r\\n16 0    : 0ms  : Version Rules: system-version:http://snomed.info/sct#http://snomed.info/sct/900000000000207008\\r\\n16 0    : 0ms  : Prepare include: \\\"(http://loinc.org)(85353-1,9279-1,8867-4,2708-6,8310-5,8302-2,9843-4,29463-7,39156-5,85354-9,8480-6,8462-4,8478-0)\\\"\\r\\n16 0    : 0ms  : CodeSystem found: \\\"http://loinc.org|2.81\\\"\\r\\n16 0    : 0ms  : Validate \\\"[http://loinc.org#8310-5 (\\\"Body temperature\\\"), http://snomed.info/sct#276885007 (\\\"Core body temperature\\\"), urn:iso:std:iso:11073:10101#150364 (\\\"\\\"), urn:iso:std:iso:11073:10101#150368 (\\\"Body temperature - Core\\\"), http://loinc.org#8329-5 (\\\"Body temperature - Core\\\")]\\\"\\r\\n16 0    : 0ms  : Check \\\"http://loinc.org#8310-5\\\"\\r\\n16 0    : 0ms  : CodeSystem found: http://loinc.org|2.81 for http://loinc.org\\r\\n16 0    : 0ms  : check code in (http://loinc.org)(85353-1,9279-1,8867-4,2708-6,8310-5,8302-2,9843-4,29463-7,39156-5,85354-9,8480-6,8462-4,8478-0) at CodeableConcept.coding[0]\\r\\n16 0    : 0ms  : Code \\\"8310-5\\\" found in http://loinc.org|2.81\\r\\n16 0    : 0ms  : Check \\\"http://snomed.info/sct#276885007\\\"\\r\\n16 0    : 0ms  : Check \\\"urn:iso:std:iso:11073:10101#150364\\\"\\r\\n31 15   : 15ms : Check \\\"urn:iso:std:iso:11073:10101#150368\\\"\\r\\n63 32   : 47ms : Check \\\"http://loinc.org#8329-5\\\"\\r\\n63 0    : 47ms : CodeSystem found: http://loinc.org|2.81 for http://loinc.org\\r\\n63 0    : 47ms : check code in (http://loinc.org)(85353-1,9279-1,8867-4,2708-6,8310-5,8302-2,9843-4,29463-7,39156-5,85354-9,8480-6,8462-4,8478-0) at CodeableConcept.coding[4]\\r\\n\"}]}",
  "devBody": "{\"resourceType\":\"Parameters\",\"parameter\":[{\"name\":\"version\",\"valueString\":\"2.81\"},{\"name\":\"result\",\"valueBoolean\":true},{\"name\":\"system\",\"valueUri\":\"http://loinc.org\"},{\"name\":\"code\",\"valueCode\":\"8310-5\"},{\"name\":\"display\",\"valueString\":\"Körpertemperatur\"},{\"name\":\"message\",\"valueString\":\"Wrong Display Name 'Body temperature - Core' for urn:iso:std:iso:11073:10101#150368. Valid display is 'MDC_TEMP_CORE' (for the language(s) 'de'); Wrong Display Name 'Body temperature' for http://loinc.org#8310-5. Valid display is one of 2 choices: 'Körpertemperatur' (de-DE) or 'Körpertemperatur' (de-AT) (for the language(s) 'de')\"},{\"name\":\"codeableConcept\",\"valueCodeableConcept\":{\"coding\":[{\"system\":\"http://loinc.org\",\"code\":\"8310-5\",\"display\":\"Body temperature\"},{\"system\":\"http://snomed.info/sct\",\"code\":\"276885007\",\"display\":\"Core body temperature\"},{\"system\":\"urn:iso:std:iso:11073:10101\",\"code\":\"150364\"},{\"system\":\"urn:iso:std:iso:11073:10101\",\"code\":\"150368\",\"display\":\"Body temperature - Core\"},{\"system\":\"http://loinc.org\",\"code\":\"8329-5\",\"display\":\"Body temperature - Core\"}]}},{\"name\":\"issues\",\"resource\":{\"resourceType\":\"OperationOutcome\",\"issue\":[{\"severity\":\"warning\",\"code\":\"invalid\",\"details\":{\"text\":\"Wrong Display Name 'Body temperature' for http://loinc.org#8310-5. Valid display is one of 2 choices: 'Körpertemperatur' (de-DE) or 'Körpertemperatur' (de-AT) (for the language(s) 'de')\",\"coding\":[{\"system\":\"http://hl7.org/fhir/tools/CodeSystem/tx-issue-type\",\"code\":\"invalid-display\"}]},\"expression\":[\"CodeableConcept.coding[0].display\"],\"extension\":[{\"url\":\"http://hl7.org/fhir/StructureDefinition/operationoutcome-message-id\",\"valueString\":\"Display_Name_for__should_be_one_of__instead_of\"}]},{\"severity\":\"information\",\"code\":\"code-invalid\",\"details\":{\"text\":\"The provided code 'http://snomed.info/sct#276885007 ('Core body temperature')' was not found in the value set 'http://hl7.org/fhir/ValueSet/observation-vitalsignresult|4.0.1'\",\"coding\":[{\"system\":\"http://hl7.org/fhir/tools/CodeSystem/tx-issue-type\",\"code\":\"this-code-not-in-vs\"}]},\"expression\":[\"CodeableConcept.coding[1].code\"],\"extension\":[{\"url\":\"http://hl7.org/fhir/StructureDefinition/operationoutcome-message-id\",\"valueString\":\"None_of_the_provided_codes_are_in_the_value_set_one\"}]},{\"severity\":\"information\",\"code\":\"code-invalid\",\"details\":{\"text\":\"The provided code 'urn:iso:std:iso:11073:10101#150364' was not found in the value set 'http://hl7.org/fhir/ValueSet/observation-vitalsignresult|4.0.1'\",\"coding\":[{\"system\":\"http://hl7.org/fhir/tools/CodeSystem/tx-issue-type\",\"code\":\"this-code-not-in-vs\"}]},\"expression\":[\"CodeableConcept.coding[2].code\"],\"extension\":[{\"url\":\"http://hl7.org/fhir/StructureDefinition/operationoutcome-message-id\",\"valueString\":\"None_of_the_provided_codes_are_in_the_value_set_one\"}]},{\"severity\":\"information\",\"code\":\"business-rule\",\"details\":{\"text\":\"Reference to draft CodeSystem urn:iso:std:iso:11073:10101|2024-12-05 from fhir.tx.support.r4#0.32.0\",\"coding\":[{\"system\":\"http://hl7.org/fhir/tools/CodeSystem/tx-issue-type\",\"code\":\"status-check\"}]},\"extension\":[{\"url\":\"http://hl7.org/fhir/StructureDefinition/operationoutcome-message-id\",\"valueString\":\"MSG_DRAFT\"}]},{\"severity\":\"information\",\"code\":\"code-invalid\",\"details\":{\"text\":\"The provided code 'urn:iso:std:iso:11073:10101#150368 ('Body temperature - Core')' was not found in the value set 'http://hl7.org/fhir/ValueSet/observation-vitalsignresult|4.0.1'\",\"coding\":[{\"system\":\"http://hl7.org/fhir/tools/CodeSystem/tx-issue-type\",\"code\":\"this-code-not-in-vs\"}]},\"expression\":[\"CodeableConcept.coding[3].code\"],\"extension\":[{\"url\":\"http://hl7.org/fhir/StructureDefinition/operationoutcome-message-id\",\"valueString\":\"None_of_the_provided_codes_are_in_the_value_set_one\"}]},{\"severity\":\"information\",\"code\":\"business-rule\",\"details\":{\"text\":\"Reference to draft CodeSystem urn:iso:std:iso:11073:10101|2024-12-05 from fhir.tx.support.r4#0.32.0\",\"coding\":[{\"system\":\"http://hl7.org/fhir/tools/CodeSystem/tx-issue-type\",\"code\":\"status-check\"}]},\"extension\":[{\"url\":\"http://hl7.org/fhir/StructureDefinition/operationoutcome-message-id\",\"valueString\":\"MSG_DRAFT\"}]},{\"severity\":\"warning\",\"code\":\"invalid\",\"details\":{\"text\":\"Wrong Display Name 'Body temperature - Core' for urn:iso:std:iso:11073:10101#150368. Valid display is 'MDC_TEMP_CORE' (for the language(s) 'de')\",\"coding\":[{\"system\":\"http://hl7.org/fhir/tools/CodeSystem/tx-issue-type\",\"code\":\"invalid-display\"}]},\"expression\":[\"CodeableConcept.coding[3].display\"],\"extension\":[{\"url\":\"http://hl7.org/fhir/StructureDefinition/operationoutcome-message-id\",\"valueString\":\"Display_Name_for__should_be_one_of__instead_of\"}]},{\"severity\":\"information\",\"code\":\"code-invalid\",\"details\":{\"text\":\"The provided code 'http://loinc.org#8329-5 ('Body temperature - Core')' was not found in the value set 'http://hl7.org/fhir/ValueSet/observation-vitalsignresult|4.0.1'\",\"coding\":[{\"system\":\"http://hl7.org/fhir/tools/CodeSystem/tx-issue-type\",\"code\":\"this-code-not-in-vs\"}]},\"expression\":[\"CodeableConcept.coding[4].code\"],\"extension\":[{\"url\":\"http://hl7.org/fhir/StructureDefinition/operationoutcome-message-id\",\"valueString\":\"None_of_the_provided_codes_are_in_the_value_set_one\"}]}]}},{\"name\":\"diagnostics\",\"valueString\":\"0ms tx-op\\n1ms http://hl7.org/fhir/ValueSet/observation-vitalsignresult|4.0.1: Analysing http://hl7.org/fhir/ValueSet/observation-vitalsignresult|4.0.1 for validation purposes\\n1ms http://hl7.org/fhir/ValueSet/observation-vitalsignresult|4.0.1: Prepare include[0]: \\\"()\\\"\\n2ms http://hl7.org/fhir/ValueSet/observation-vitalsignresult|4.0.1: CodeSystem found: \\\"http://loinc.org|2.81\\\"\\n2ms http://hl7.org/fhir/ValueSet/observation-vitalsignresult|4.0.1: Validate \\\"[undefined#8310-5 (\\\"Body temperature\\\"), undefined#276885007 (\\\"Core body temperature\\\"), undefined#150364 (\\\"undefined\\\"), undefined#150368 (\\\"Body temperature - Core\\\"), undefined#8329-5 (\\\"Body temperature - Core\\\")]\\\"\\n3ms http://hl7.org/fhir/ValueSet/observation-vitalsignresult|4.0.1: Check \\\"http://loinc.org#8310-5\\\"\\n5ms http://hl7.org/fhir/ValueSet/observation-vitalsignresult|4.0.1: CodeSystem found: http://loinc.org|2.81 for http://loinc.org\\n5ms http://hl7.org/fhir/ValueSet/observation-vitalsignresult|4.0.1: check code in () at CodeableConcept.coding[0]\\n5ms http://hl7.org/fhir/ValueSet/observation-vitalsignresult|4.0.1: Code \\\"8310-5\\\" found in http://loinc.org|2.81\\n5ms http://hl7.org/fhir/ValueSet/observation-vitalsignresult|4.0.1: Check \\\"http://snomed.info/sct#276885007\\\"\\n5ms http://hl7.org/fhir/ValueSet/observation-vitalsignresult|4.0.1: Check \\\"urn:iso:std:iso:11073:10101#150364\\\"\\n5ms http://hl7.org/fhir/ValueSet/observation-vitalsignresult|4.0.1: Check \\\"urn:iso:std:iso:11073:10101#150368\\\"\\n6ms http://hl7.org/fhir/ValueSet/observation-vitalsignresult|4.0.1: Check \\\"http://loinc.org#8329-5\\\"\\n8ms http://hl7.org/fhir/ValueSet/observation-vitalsignresult|4.0.1: CodeSystem found: http://loinc.org|2.81 for http://loinc.org\\n8ms http://hl7.org/fhir/ValueSet/observation-vitalsignresult|4.0.1: check code in () at CodeableConcept.coding[4]\"}]}",
  "requestBody": "{\"resourceType\":\"Parameters\",\"parameter\":[{\"name\":\"codeableConcept\",\"valueCodeableConcept\":{\"coding\":[{\"system\":\"http://loinc.org\",\"code\":\"8310-5\",\"display\":\"Body temperature\"},{\"system\":\"http://snomed.info/sct\",\"code\":\"276885007\",\"display\":\"Core body temperature\"},{\"system\":\"urn:iso:std:iso:11073:10101\",\"code\":\"150364\"},{\"system\":\"urn:iso:std:iso:11073:10101\",\"code\":\"150368\",\"display\":\"Body temperature - Core\"},{\"system\":\"http://loinc.org\",\"code\":\"8329-5\",\"display\":\"Body temperature - Core\"}]}},{\"name\":\"displayLanguage\",\"valueString\":\"de\"},{\"name\":\"lenient-display-validation\",\"valueBoolean\":true},{\"name\":\"default-to-latest-version\",\"valueBoolean\":true},{\"name\":\"valueSet\",\"resource\":{\"resourceType\":\"ValueSet\",\"id\":\"observation-vitalsignresult\",\"meta\":{\"lastUpdated\":\"2019-11-01T09:29:23.356+11:00\",\"profile\":[\"http://hl7.org/fhir/StructureDefinition/shareablevalueset\"]},\"extension\":[{\"url\":\"http://hl7.org/fhir/StructureDefinition/structuredefinition-wg\",\"valueCode\":\"oo\"}],\"url\":\"http://hl7.org/fhir/ValueSet/observation-vitalsignresult\",\"identifier\":[{\"system\":\"urn:ietf:rfc:3986\",\"value\":\"urn:oid:2.16.840.1.113883.3.88.12.80.62\"}],\"version\":\"4.0.1\",\"name\":\"VitalSigns\",\"title\":\"Vital Signs\",\"status\":\"active\",\"experimental\":false,\"date\":\"2019-11-01T09:29:23+11:00\",\"publisher\":\"FHIR project team\",\"contact\":[{\"telecom\":[{\"system\":\"url\",\"value\":\"http://hl7.org/fhir\"}]}],\"description\":\"This value set indicates the allowed vital sign result types.   The LOINC code for Vitals Signs panel (85353-1) is a grouping structure for a set of vital signs and includes related links (with type=has-member) to the Observations in this set (e.g. respiratory rate, heart rate, BP).  The Blood pressure panel (85354-9) is used to group the component observations Systolic blood pressure (8480-6) and Diastolic blood pressure (8462-4).\",\"copyright\":\"This content from LOINC® is copyright © 1995 Regenstrief Institute, Inc. and the LOINC Committee, and available at no cost under the license at http://loinc.org/terms-of-use\",\"compose\":{\"include\":[{\"system\":\"http://loinc.org\",\"concept\":[{\"code\":\"85353-1\"},{\"code\":\"9279-1\"},{\"code\":\"8867-4\"},{\"code\":\"2708-6\"},{\"code\":\"8310-5\"},{\"code\":\"8302-2\"},{\"code\":\"9843-4\"},{\"code\":\"29463-7\"},{\"code\":\"39156-5\"},{\"code\":\"85354-9\"},{\"code\":\"8480-6\"},{\"code\":\"8462-4\"},{\"code\":\"8478-0\"}]}]}}},{\"name\":\"cache-id\",\"valueId\":\"682b9794-e6ca-4120-b516-17382b3aff31\"},{\"name\":\"profile-url\",\"valueString\":\"http://hl7.org/fhir/ExpansionProfile/dc8fd4bc-091a-424a-8a3b-6198ef146891\"},{\"name\":\"system-version\",\"valueCanonical\":\"http://snomed.info/sct|http://snomed.info/sct/900000000000207008\"},{\"name\":\"mode\",\"valueString\":\"lenient-display-validation\"},{\"name\":\"diagnostics\",\"valueBoolean\":true}]}"
}